arrakis_nd/__init__.py
arrakis_nd/arrakis/__init__.py
arrakis_nd/arrakis/arrakis.py
arrakis_nd/arrakis/common.py
arrakis_nd/dataset/__init__.py
arrakis_nd/dataset/common.py
arrakis_nd/plugins/__init__.py
arrakis_nd/plugins/ancestor_plugin.py
arrakis_nd/plugins/blip_plugin.py
arrakis_nd/plugins/constraint_plugin.py
arrakis_nd/plugins/daughter_plugin.py
arrakis_nd/plugins/delta_plugin.py
arrakis_nd/plugins/empty_plugin.py
arrakis_nd/plugins/fragment_plugin.py
arrakis_nd/plugins/interaction_plugin.py
arrakis_nd/plugins/ion_plugin.py
arrakis_nd/plugins/michel_plugin.py
arrakis_nd/plugins/neutrino_plugin.py
arrakis_nd/plugins/neutron_plugin.py
arrakis_nd/plugins/parent_plugin.py
arrakis_nd/plugins/particle_plugin.py
arrakis_nd/plugins/photon_plugin.py
arrakis_nd/plugins/plugin.py
arrakis_nd/plugins/proton_plugin.py
arrakis_nd/plugins/segment_plugin.py
arrakis_nd/plugins/shower_plugin.py
arrakis_nd/plugins/track_plugin.py
arrakis_nd/plugins/trackid_hit_map.py
arrakis_nd/programs/__init__.py
arrakis_nd/programs/create_arrakis_runs.py
arrakis_nd/programs/plugin_creator.py
arrakis_nd/programs/run_arrakis.py
arrakis_nd/programs/run_arrakis_display.py
arrakis_nd/utils/__init__.py
arrakis_nd/utils/common.py
arrakis_nd/utils/config.py
arrakis_nd/utils/geometry.py
arrakis_nd/utils/logger.py
arrakis_nd/utils/shower_utils.py
arrakis_nd/utils/track_utils.py
arrakis_nd/utils/utils.py
arrakis_nd/utils/display/__init__.py
arrakis_nd/utils/display/arrakis_display.py
arrakis_nd/utils/display/charge_light_display.py
arrakis_nd/utils/display/marjolein_2x2_display.py
arrakis_nd/utils/display/set_server.py
arrakis_nd/utils/display/utils.py
arrakis_nd/utils/display/vis_event.py
arrakis_nd-2.0.2.dist-info/AUTHORS.md
arrakis_nd-2.0.2.dist-info/LICENSE
arrakis_nd-2.0.2.dist-info/METADATA
arrakis_nd-2.0.2.dist-info/WHEEL
arrakis_nd-2.0.2.dist-info/entry_points.txt
arrakis_nd-2.0.2.dist-info/top_level.txt
arrakis_nd-2.0.2.dist-info/RECORD
