Metadata-Version: 2.1
Name: arrakis_nd
Version: 2.0.2
Summary: Arrakis module for near detector data.
Home-page: https://github.com/Neutron-Calibration-in-DUNE/ArrakisND
Author: Nicholas Carrara, Marjolein van Nuland, Luis Lepin
Author-email: ncarrara.physics@gmail.com
Classifier: Development Status :: 3 - Alpha
Classifier: Intended Audience :: Science/Research
Classifier: License :: OSI Approved :: GNU General Public License (GPL)
Classifier: Natural Language :: English
Classifier: Operating System :: OS Independent
Classifier: Programming Language :: Python :: 3
Requires-Python: >3.7
License-File: LICENSE
License-File: AUTHORS.md
Requires-Dist: asttokens
Requires-Dist: bleach
Requires-Dist: bokeh
Requires-Dist: Brotli
Requires-Dist: cached-property
Requires-Dist: certifi
Requires-Dist: cffi ==1.16.0
Requires-Dist: charset-normalizer
Requires-Dist: colorama
Requires-Dist: colorcet ==3.1.0
Requires-Dist: comm
Requires-Dist: contourpy
Requires-Dist: cryptography ==42.0.5
Requires-Dist: cycler
Requires-Dist: dash
Requires-Dist: dash-bootstrap-components
Requires-Dist: debugpy
Requires-Dist: decorator
Requires-Dist: docutils ==0.20.1
Requires-Dist: exceptiongroup
Requires-Dist: executing
Requires-Dist: fonttools
Requires-Dist: h5py
Requires-Dist: holoviews ==1.18.3
Requires-Dist: idna
Requires-Dist: importlib-metadata
Requires-Dist: ipykernel
Requires-Dist: ipython
Requires-Dist: jaraco.classes ==3.3.1
Requires-Dist: jedi
Requires-Dist: jeepney ==0.8.0
Requires-Dist: Jinja2
Requires-Dist: jupyter-client
Requires-Dist: jupyter-core
Requires-Dist: keyring ==24.3.1
Requires-Dist: kiwisolver
Requires-Dist: linkify-it-py
Requires-Dist: Markdown
Requires-Dist: markdown-it-py
Requires-Dist: MarkupSafe
Requires-Dist: matplotlib
Requires-Dist: matplotlib-inline
Requires-Dist: mdit-py-plugins
Requires-Dist: mdurl
Requires-Dist: more-itertools ==10.2.0
Requires-Dist: mpi4py
Requires-Dist: munkres ==1.1.4
Requires-Dist: nest-asyncio
Requires-Dist: nh3 ==0.2.15
Requires-Dist: nodejs ==0.1.1
Requires-Dist: numpy
Requires-Dist: optional-django ==0.1.0
Requires-Dist: packaging
Requires-Dist: pandas
Requires-Dist: panel
Requires-Dist: param
Requires-Dist: parso
Requires-Dist: pexpect
Requires-Dist: pickleshare
Requires-Dist: pillow
Requires-Dist: pkginfo ==1.10.0
Requires-Dist: platformdirs
Requires-Dist: plotly ==5.19.0
Requires-Dist: ply ==3.11
Requires-Dist: prompt-toolkit
Requires-Dist: psutil
Requires-Dist: ptyprocess
Requires-Dist: pure-eval
Requires-Dist: pycparser ==2.21
Requires-Dist: Pygments
Requires-Dist: pyparsing
Requires-Dist: PyQt5 ==5.15.9
Requires-Dist: PyQt5-sip ==12.12.2
Requires-Dist: PySocks
Requires-Dist: python-dateutil
Requires-Dist: pytz
Requires-Dist: pyviz-comms
Requires-Dist: PyYAML
Requires-Dist: pyzmq
Requires-Dist: readme-renderer ==43.0
Requires-Dist: requests
Requires-Dist: requests-toolbelt ==1.0.0
Requires-Dist: rfc3986 ==2.0.0
Requires-Dist: rich ==13.7.1
Requires-Dist: scipy
Requires-Dist: SecretStorage ==3.3.3
Requires-Dist: setuptools ==69.1.1
Requires-Dist: sip
Requires-Dist: six
Requires-Dist: stack-data
Requires-Dist: toml
Requires-Dist: tomli
Requires-Dist: tornado
Requires-Dist: tqdm
Requires-Dist: traitlets
Requires-Dist: twine ==5.0.0
Requires-Dist: typing-extensions
Requires-Dist: tzdata
Requires-Dist: uc-micro-py
Requires-Dist: urllib3
Requires-Dist: wcwidth
Requires-Dist: webencodings
Requires-Dist: wheel ==0.42.0
Requires-Dist: xyzservices
Requires-Dist: zipp
